rasa_dialogflow_interpreter/__init__.py
rasa_dialogflow_interpreter/interpreter.py
rasa_dialogflow_interpreter-0.6.0.dist-info/METADATA
rasa_dialogflow_interpreter-0.6.0.dist-info/RECORD
rasa_dialogflow_interpreter-0.6.0.dist-info/WHEEL
rasa_dialogflow_interpreter-0.6.0.dist-info/top_level.txt
