Metadata-Version: 2.1
Name: rasa-dialogflow-interpreter
Version: 0.6.0
Summary: rasa_core interpreter connecting to dialogflow.com API v2
Home-page: https://github.com/m90/rasa-dialogflow-interpreter
Author: Frederik Ring
Author-email: frederik.ring@gmail.com
License: UNKNOWN
Platform: UNKNOWN
Classifier: Programming Language :: Python :: 3
Classifier: License :: OSI Approved :: MIT License
Classifier: Operating System :: OS Independent
Requires-Dist: dialogflow (~=0.4)
Requires-Dist: rasa-core (~=0.14)
